<?xml version='1.0' encoding='UTF-8'?>
<hudson.plugins.sonar.SonarPublisher_-DescriptorImpl plugin="sonar@2.2.1">
  <installations>
    <hudson.plugins.sonar.SonarInstallation>
      <name>SONAR</name>
      <disabled>false</disabled>
      <serverUrl>http://localhost:9080/sonar</serverUrl>
      <mojoVersion></mojoVersion>
      <databaseUrl></databaseUrl>
      <databaseLogin></databaseLogin>
      <additionalProperties></additionalProperties>
      <triggers>
        <skipScmCause>false</skipScmCause>
        <skipUpstreamCause>false</skipUpstreamCause>
        <envVar></envVar>
      </triggers>
      <sonarLogin>sonar</sonarLogin>
    </hudson.plugins.sonar.SonarInstallation>
  </installations>
</hudson.plugins.sonar.SonarPublisher_-DescriptorImpl>